LICENSE
MANIFEST.in
README.rst
setup.py
tests/test_auto_clear.py
tests/test_delete_cache.py
tests/test_excessive_attempts.py
tests/test_hidden.py
tests/test_hostname.py
tests/test_input.py
tests/test_ip_validator.py
tests/test_multiline.py
tests/test_sanitizer.py
tests/test_start.py
tests/test_version.py
userinput/__init__.py
userinput/__version__.py
userinput/set_recoverer.py
userinput/userinput.py
userinput.egg-info/PKG-INFO
userinput.egg-info/SOURCES.txt
userinput.egg-info/dependency_links.txt
userinput.egg-info/requires.txt
userinput.egg-info/top_level.txt
userinput/test/__init__.py
userinput/test/simulate_multiline.py
userinput/utils/__init__.py
userinput/utils/clear.py
userinput/utils/closest.py
userinput/utils/default_sanitizers.py
userinput/utils/default_validators.py
userinput/utils/set_validator.py
userinput/utils/start.py