Metadata-Version: 2.1
Name: userinput
Version: 1.0.22
Summary: Simple python package to handle cli user input.
Home-page: https://github.com/LucaCappelletti94/userinput
Author: Luca Cappelletti
Author-email: cappelletti.luca94@gmail.com
License: MIT
Classifier: Development Status :: 3 - Alpha
Classifier: License :: OSI Approved :: MIT License
Classifier: Programming Language :: Python :: 3
Provides-Extra: test
License-File: LICENSE
